pyredpen-0.0.5.dist-info/DESCRIPTION.rst
pyredpen-0.0.5.dist-info/entry_points.txt
pyredpen-0.0.5.dist-info/METADATA
pyredpen-0.0.5.dist-info/metadata.json
pyredpen-0.0.5.dist-info/RECORD
pyredpen-0.0.5.dist-info/top_level.txt
pyredpen-0.0.5.dist-info/WHEEL
redpen/__init__.py
redpen/client.py
redpen/default.py
redpen/flymake.py
redpen/shell.py
