Metadata-Version: 2.0
Name: pyredpen
Version: 0.0.5
Summary: Client for RedPen, a text validator
Home-page: https://github.com/taky/pyredpen
Author: Takahiro Yoshimura
Author-email: altakey@gmail.com
License: UNKNOWN
Keywords: natural language processing japanese english correction
Platform: UNKNOWN
Classifier: Programming Language :: Python
Requires-Dist: urllib3
